pisque.py
pisque-0.1.0.dist-info/entry_points.txt
pisque-0.1.0.dist-info/WHEEL
pisque-0.1.0.dist-info/METADATA
pisque-0.1.0.dist-info/RECORD
