Metadata-Version: 2.1
Name: pisque
Version: 0.1.0
Summary: Install Python packages in an isolated virtual environment
License: BSD
Author: Tim Heap
Author-email: tim@timheap.me
Requires-Python: >=3.7,<4.0
Classifier: License :: Other/Proprietary License
Classifier: Programming Language :: Python :: 3
Classifier: Programming Language :: Python :: 3.10
Classifier: Programming Language :: Python :: 3.7
Classifier: Programming Language :: Python :: 3.8
Classifier: Programming Language :: Python :: 3.9
Requires-Dist: ConfigArgParse[yaml] (>=1.5.3,<2.0.0)
